[
  {
    "race": {
      "white": 680,
      "black": 739,
      "asian": 691,
      "caucasian": 724,
      "alaska native": 712,
      "native hawaiian": 735,
      "NA": 719
    },
    "gender": {
      "male": 437,
      "female": 469,
      "man": 454,
      "woman": 490,
      "guy": 451,
      "gentleman": 443,
      "lady": 449,
      "Bigender": 422,
      "teenager": 470,
      "adult": 450,
      "NA": 465
    },
    "hair_style": {
      "straight": 1012,
      "wavy": 962,
      "curly": 990,
      "kinky": 1016,
      "NA": 1020
    },
    "hair_color": {
      "black": 465,
      "white": 443,
      "blond": 456,
      "gray": 403,
      "brown": 431,
      "red": 446,
      "auburn": 466,
      "chestnut": 453,
      "dark": 459,
      "light": 513,
      "NA": 465
    },
    "hair_len": {
      "short": 1261,
      "long": 1265,
      "middle": 1241,
      "NA": 1233
    },
    "top": {
      "suit": 158,
      "shirt": 133,
      "dress": 153,
      "blouse": 142,
      "tanktop": 141,
      "coat": 157,
      "jacket": 147,
      "T-shirt": 137,
      "jumper": 148,
      "pullover": 120,
      "cardigan": 150,
      "sweatshirt": 130,
      "hoodie": 132,
      "checked shirt": 132,
      "sweater": 145,
      "Hawaiian shirt": 161,
      "Turtleneck shirt": 146,
      "polo shirt": 137,
      "short-sleeved shirt": 154,
      "pojama": 148,
      "singlet": 131,
      "vest": 150,
      "bathrobe": 131,
      "jersey": 138,
      "anorak": 143,
      "blazer": 303,
      "blousegown": 142,
      "tank yop": 132,
      "trench coat": 153,
      "camp shirt": 148,
      "peacoat": 145,
      "down": 141,
      "bomber": 134,
      "NA": 138
    },
    "top_color": {
      "red": 378,
      "orange": 394,
      "yellow": 386,
      "green": 364,
      "blue": 348,
      "violet": 368,
      "black": 399,
      "white": 358,
      "gold": 334,
      "silver": 377,
      "pink": 356,
      "gray": 396,
      "NA": 542
    },
    "bottom": {
      "skirt": 285,
      "trousers": 312,
      "jeans": 294,
      "shorts": 316,
      "pants": 305,
      "track pants": 310,
      "cargo pants": 325,
      "half pant": 322,
      "mini scart": 316,
      "joggers": 325,
      "briefs": 336,
      "ruffled skirt": 291,
      "jeans skirt": 313,
      "jeans shorts": 336,
      "cropped jeans": 314,
      "NA": 300
    },
    "bottom_color": {
      "red": 340,
      "orange": 378,
      "yellow": 373,
      "green": 357,
      "blue": 381,
      "violet": 402,
      "black": 351,
      "white": 350,
      "gold": 370,
      "silver": 355,
      "pink": 328,
      "gray": 348,
      "NA": 667
    },
    "footwear": {
      "shoes": 368,
      "sandals": 303,
      "boots": 355,
      "slippers": 367,
      "sneakers": 354,
      "wellingtons": 351,
      "loafers": 353,
      "straps": 348,
      "docksiders": 370,
      "flops": 356,
      "high heels": 340,
      "running shoes": 344,
      "hiking boots": 387,
      "NA": 404
    },
    "footwear_color": {
      "red": 373,
      "orange": 332,
      "yellow": 368,
      "green": 367,
      "blue": 346,
      "violet": 364,
      "black": 353,
      "white": 349,
      "gold": 349,
      "silver": 325,
      "pink": 357,
      "gray": 338,
      "NA": 779
    },
    "accessory": {
      "hat": 143,
      "belt": 149,
      "handbag": 145,
      "glasses": 157,
      "scarf": 168,
      "sunglasses": 143,
      "gloves": 144,
      "bracelet": 171,
      "necklace": 176,
      "ring": 161,
      "earrings": 159,
      "cap": 145,
      "backpack": 159,
      "knife": 128,
      "gun": 162,
      "package": 159,
      "boom": 147,
      "watch": 135,
      "tie": 164,
      "umbrella": 172,
      "cigarette": 170,
      "eyepatch": 142,
      "headband": 150,
      "cloak": 162,
      "mittens": 152,
      "straw hat": 150,
      "phone": 163,
      "wallet": 167,
      "purse": 151,
      "suitcase": 150,
      "headscarf": 177,
      "NA": 179
    },
    "accessory_color": {
      "red": 356,
      "orange": 371,
      "yellow": 388,
      "green": 343,
      "blue": 379,
      "violet": 382,
      "black": 365,
      "white": 385,
      "gold": 363,
      "silver": 348,
      "pink": 397,
      "gray": 366,
      "NA": 557
    }
  }
]
